pure_interface/__init__.py
pure_interface/_sub_interface.py
pure_interface/adaption.py
pure_interface/delegation.py
pure_interface/errors.py
pure_interface/interface.py
pure_interface/mypy_plugin.py
pure_interface/py.typed
pure_interface-8.0.4.dist-info/licenses/LICENSE
pure_interface-8.0.4.dist-info/METADATA
pure_interface-8.0.4.dist-info/WHEEL
pure_interface-8.0.4.dist-info/top_level.txt
pure_interface-8.0.4.dist-info/RECORD
