Metadata-Version: 2.4
Name: pure-interface
Version: 8.0.4
Summary: A Python interface library that disallows function body content on interfaces and supports adaption.
Author-email: Tim Mitchell <tim.mitchell@seequent.com>
License-Expression: MIT
Project-URL: Homepage, https://pypi.org/project/pure-interface/
Project-URL: Repository, https://github.com/seequent/pure_interface
Keywords: interface,protocol,adaption,structural,dataclass
Classifier: Development Status :: 5 - Production/Stable
Classifier: Intended Audience :: Developers
Classifier: Topic :: Software Development :: Libraries
Classifier: Programming Language :: Python :: 3.9
Classifier: Programming Language :: Python :: 3.10
Classifier: Programming Language :: Python :: 3.11
Classifier: Programming Language :: Python :: 3.12
Classifier: Programming Language :: Python :: 3.13
Requires-Python: >=3.9
License-File: LICENSE
Provides-Extra: dev
Requires-Dist: mypy>=1.4; extra == "dev"
Requires-Dist: tox; extra == "dev"
Provides-Extra: typing
Requires-Dist: mypy; extra == "typing"
Dynamic: license-file
